{
  "$schema": "https://raw.githubusercontent.com/Bobini1/RhythmGame/refs/heads/master/schemas/themeSettings.json",
  "items": [
    {
      "id": "sortOrder",
      "name": {
        "en": "Sort Order",
        "pl": "Kolejność sortowania"
      },
      "description": {
        "en": "The sort order of songs.",
        "pl": "Kolejność sortowania piosenek."
      },
      "type": "choice",
      "default": "title",
      "choices": [
        {
          "name": {
            "en": "Title",
            "pl": "Tytuł"
          },
          "value": "title"
        },
        {
          "name": {
            "en": "Artist",
            "pl": "Artysta"
          },
          "value": "artist"
        },
        {
          "name": {
            "en": "BPM",
            "pl": "BPM"
          },
          "value": "bpm"
        },
        {
          "name": {
            "en": "Clear",
            "pl": "Clear"
          },
          "value": "clear"
        },
        {
          "name": {
            "en": "Score",
            "pl": "Punkty"
          },
          "value": "score"
        },
        {
          "name": {
            "en": "Level",
            "pl": "Poziom"
          },
          "value": "level"
        },
        {
          "name": {
            "en": "Total",
            "pl": "total"
          },
          "value": "total"
        }
      ]
    },
    {
      "id": "keymodeFilter",
        "name": {
            "en": "Keymode Filter",
            "pl": "Filtr ilości klawiszy"
        },
        "description": {
            "en": "Filter songs by keymode.",
            "pl": "Filtrowanie piosenek według ilości klawiszy."
        },
        "type": "choice",
        "default": "7",
        "choices": [
            {
                "name": {
                    "en": "7K",
                    "pl": "7K"
                },
                "value": "7"
            },
            {
                "name": {
                    "en": "14K",
                    "pl": "14K"
                },
                "value": "14"
            },
            {
                "name": {
                    "en": "All keys",
                    "pl": "Wszystkie"
                },
                "value": ""
            }
        ]
    }
  ]
}